token_manager/__init__.py
token_manager/admin.py
token_manager/authentication.py
token_manager/compat.py
token_manager/models.py
token_manager/serializers.py
token_manager/settings.py
token_manager/urls.py
token_manager/utils.py
token_manager/views.py
token_manager/migrations/0001_initial.py
token_manager/migrations/0002_tokenlookupid_user.py
token_manager/migrations/__init__.py
django_token_manager-1.1.2.dist-info/LICENSE
django_token_manager-1.1.2.dist-info/METADATA
django_token_manager-1.1.2.dist-info/WHEEL
django_token_manager-1.1.2.dist-info/top_level.txt
django_token_manager-1.1.2.dist-info/RECORD
