Metadata-Version: 2.1
Name: django-token-manager
Version: 1.1.2
Summary: A Django Rest Token Authentication system like telegram which will be using JWT as core with extended features.
Home-page: https://github.com/Execut3/django-token-manager
Author: Execut3
Author-email: execut3.binarycodes@gmail.com
License: GPT
Platform: UNKNOWN
Requires-Dist: Django (>=2.0)
Requires-Dist: djangorestframework (>=3.0)
Requires-Dist: django-jalali (>=3.1.0)
Requires-Dist: django-rest-captcha (==0.1.0)
Requires-Dist: django-user-agents (>=0.3.2)
